__init__.py
tinyvec2.py
tinyvec2d-0.1.0.dist-info/licenses/LICENSE.txt
tinyvec2d-0.1.0.dist-info/METADATA
tinyvec2d-0.1.0.dist-info/WHEEL
tinyvec2d-0.1.0.dist-info/top_level.txt
tinyvec2d-0.1.0.dist-info/RECORD
