Metadata-Version: 2.4
Name: tinyvec2d
Version: 0.1.0
Summary: Tiny 2D vector helpers, no NumPy, no classes.
Author: Melvin
License: MIT
Requires-Python: >=3.9
License-File: LICENSE.txt
Dynamic: license-file
